LICENSE
README.md
setup.py
src/envil.py
src/envil.egg-info/PKG-INFO
src/envil.egg-info/SOURCES.txt
src/envil.egg-info/dependency_links.txt
src/envil.egg-info/top_level.txt