Metadata-Version: 2.1
Name: envil
Version: 0.2.0
Summary: Get non-string values from environment variables.
Home-page: https://github.com/luismsgomes/envil
Author: Luís Gomes
Author-email: luismsgomes@gmail.com
License: GPLv3
Keywords: util
Classifier: Development Status :: 4 - Beta
Classifier: License :: OSI Approved :: GNU General Public License v3 (GPLv3)
Classifier: Programming Language :: Python :: 3.8
License-File: LICENSE
